costack_cli/__init__.py
costack_cli/build_project.py
costack_cli/config.py
costack_cli/constants.py
costack_cli/integrations.py
costack_cli/local_test.py
costack_cli/login.py
costack_cli/main.py
costack_cli/sample_files.py
costack_cli/utils/__init__.py
costack_cli/utils/aws_helpers.py
costack_cli/utils/requests.py
costack_cli-0.2.3.dist-info/entry_points.txt
costack_cli-0.2.3.dist-info/WHEEL
costack_cli-0.2.3.dist-info/METADATA
costack_cli-0.2.3.dist-info/RECORD
