Metadata-Version: 2.1
Name: costack-cli
Version: 0.2.3
Summary: 
Author: perseus.yang
Author-email: ry82@cornell.edu
Requires-Python: >=3.7,<4.0
Classifier: Programming Language :: Python :: 3
Classifier: Programming Language :: Python :: 3.10
Classifier: Programming Language :: Python :: 3.7
Classifier: Programming Language :: Python :: 3.8
Classifier: Programming Language :: Python :: 3.9
Requires-Dist: awscli (>=1.22.23,<2.0.0)
Requires-Dist: boto3 (>=1.20.23,<2.0.0)
Requires-Dist: emoji (>=1.7.0,<2.0.0)
Requires-Dist: halo (>=0.0.31,<0.0.32)
Requires-Dist: inquirer (>=2.9.1,<3.0.0)
Requires-Dist: pyOpenSSL (>=22.0.0,<23.0.0)
Requires-Dist: requests (>=2.26.0,<3.0.0)
